pynaco/__init__.py
pynaco/naco.py
tests/__init__.py
tests/naco_test.py
tests/data/NACO.script
tests/data/NACOsimplified.check
tests/data/NACOstandard.check
pynaco-1.0.0.dist-info/LICENSE
pynaco-1.0.0.dist-info/METADATA
pynaco-1.0.0.dist-info/WHEEL
pynaco-1.0.0.dist-info/top_level.txt
pynaco-1.0.0.dist-info/RECORD
