Metadata-Version: 2.1
Name: pynaco
Version: 1.0.0
Summary: Python implementation of the NACO normalization rules.
Home-page: https://github.com/unt-libraries/pynaco
Maintainer: Mark Phillips
Maintainer-email: mark.phillips@unt.edu
License: OCLC Research Public License 2.0
Platform: UNKNOWN
Classifier: Intended Audience :: Developers
Classifier: Natural Language :: English
Classifier: Programming Language :: Python
Classifier: Programming Language :: Python :: 3.7
License-File: LICENSE
